Woche 9/submission_22_06_12_boden_seppelt_orgler/xor_3.sv
module xor_3 ( input  logic i_in0,
                            i_in1,
                            i_in2,
               output logic o_res );
               
	logic l_res1;
               
	assign l_res1 = i_in0 ^ i_in1;

	assign o_res = l_res1 ^ i_in2;

endmodule

Woche 9/submission_22_06_12_boden_seppelt_orgler/xor_3_tb.sv
module xor_3_tb;

	logic l_in0, l_in1, l_in2, l_res;
	xor_3 dut ( l_in0, l_in1, l_in2, l_res);

	initial begin
	$dumpfile("dump_xor_3.vcd");
	$dumpvars;
	
	l_in0 = 1'b0;
	l_in1 = 1'b0;
	l_in2 = 1'b0;
	#10;
	assert( l_res === 1'b0 );
	
	l_in0 = 1'b1;
	l_in1 = 1'b0;
	l_in2 = 1'b0;
	#10;
	assert( l_res === 1'b1 );
	
	l_in0 = 1'b0;
	l_in1 = 1'b1;
	l_in2 = 1'b0;
	#10;
	assert( l_res === 1'b1 );
	
	l_in0 = 1'b0;
	l_in1 = 1'b0;
	l_in2 = 1'b1;
	#10;
	assert( l_res === 1'b1 );
	
	l_in0 = 1'b1;
	l_in1 = 1'b1;
	l_in2 = 1'b0;
	#10;
	assert( l_res === 1'b0 );
	
	l_in0 = 1'b0;
	l_in1 = 1'b1;
	l_in2 = 1'b1;
	#10;
	assert( l_res === 1'b0 );
	
	l_in0 = 1'b1;
	l_in1 = 1'b0;
	l_in2 = 1'b1;
	#10;
	assert( l_res === 1'b0 );
	
	l_in0 = 1'b1;
	l_in1 = 1'b1;
	l_in2 = 1'b1;
	#10;
	assert( l_res === 1'b1 );
	
	$finish;
	end
endmodule

Woche 9/dump_xor_3.vcd
$date
	Thu Jun  9 10:48:58 2022
$end
$version
	Icarus Verilog
$end
$timescale
	1s
$end
$scope module xor_3_tb $end
$var wire 1 ! l_res $end
$var reg 1 " l_in0 $end
$var reg 1 # l_in1 $end
$var reg 1 $ l_in2 $end
$scope module dut $end
$var wire 1 " i_in0 $end
$var wire 1 # i_in1 $end
$var wire 1 $ i_in2 $end
$var wire 1 % l_res1 $end
$var wire 1 ! o_res $end
$upscope $end
$upscope $end
$enddefinitions $end
#0
$dumpvars
0%
0$
0#
0"
0!
$end
#10
1!
1%
1"
#20
1#
0"
#30
0%
1$
0#
#40
0!
0$
1#
1"
#50
1%
1$
0"
#60
0#
1"
#70
1!
0%
1#
