Woche 12/submission_22_07_03_boden_seppelt_orgler/decoder.sv
/**
 * Decoder for a seven-segment display.
 *
 * @param i_binary_number input binary number.
 * @param o_display output bits driving the seven-segment display.
 **/
module decoder( input  logic [3:0] i_binary_number,
                output logic [6:0] o_display );
  always_comb
  begin
    case( i_binary_number )
      4'b0000: o_display[6:0] = 7'b100_0000; // 0
      4'b0001: o_display[6:0] = 7'b111_1001; // 1
      4'b0010: o_display[6:0] = 7'b010_0100; // 2
      4'b0011: o_display[6:0] = 7'b011_0000; // 3
      4'b0100: o_display[6:0] = 7'b001_1001; // 4
      4'b0101: o_display[6:0] = 7'b001_0010; // 5
      4'b0110: o_display[6:0] = 7'b000_0010; // 6
      4'b0111: o_display[6:0] = 7'b111_1000; // 7
      4'b1000: o_display[6:0] = 7'b000_0000; // 8
      4'b1001: o_display[6:0] = 7'b001_0000; // 9
      4'b1010: o_display[6:0] = 7'b000_1000; // A
      4'b1011: o_display[6:0] = 7'b000_0011; // B
      4'b1100: o_display[6:0] = 7'b100_0110; // C
      4'b1101: o_display[6:0] = 7'b010_0001; // D
      4'b1110: o_display[6:0] = 7'b000_0110; // E
      4'b1111: o_display[6:0] = 7'b000_1110; // F
      // none
      default: o_display[6:0] = 7'bxxx_xxxx;
    endcase
  end
endmodule

Woche 9/submission_22_06_12_boden_seppelt_orgler/xor_3.sv
module xor_3 ( input  logic i_in0,
                            i_in1,
                            i_in2,
               output logic o_res );
               
	logic l_res1;
               
	assign l_res1 = i_in0 ^ i_in1;

	assign o_res = l_res1 ^ i_in2;

endmodule

Woche 8/mux_2.sv
module mux_2 #(parameter N=64) ( input  logic [N-1:0] i_in0,
                                                      i_in1,
                                 input  logic         i_s,
                                 output logic [N-1:0] o_out );
  assign o_out = i_s ? i_in1 : i_in0;
endmodule

Woche 9/alu_basic/mux_4.sv
/**
 * Multiplexer with four inputs.
 *
 * @param i_in0 first input.
 * @param i_in1 second input.
 * @param i_in2 third input.
 * @param i_in3 fourth input.
 * @param i_s control signal,
              if 00: in0 is output.
              if 01: in1 is output.
              if 10: in2 is output.
              if 11: in3 is output.
 * @param o_out output.
 **/
module mux_4 #(parameter N=64) ( input  logic [N-1:0] i_in0,
                                                      i_in1,
                                                      i_in2,
                                                      i_in3,
                                 input  logic [1:0]   i_s,
                                 output logic [N-1:0] o_out );
  logic [N-1:0] l_low, l_high;

  mux_2 #(N) mux_low( i_in0,
                      i_in1,
                      i_s[0],
                      l_low );

  mux_2 #(N) mux_high( i_in2,
                       i_in3,
                       i_s[0],
                       l_high );

  mux_2 #(N) mux_final( l_low,
                        l_high,
                        i_s[1],
                        o_out );
endmodule

Woche 9/submission_22_06_12_boden_seppelt_orgler/alu_basic/adder.sv
/**
 * Adder with a carry-in and carry-out.
 *
 * @param i_a first addend.
 * @param i_b second addend.
 * @param i_carry_in input carry.
 * @param o_c sum.
 * @param o_carry_out output carry.
 **/
module adder #(parameter N=64) ( input  logic [N-1:0] i_a,
                                                      i_b,
                                 input  logic         i_carry_in,
                                 output logic [N-1:0] o_c,
                                 output logic         o_carry_out );
  assign { o_carry_out, o_c } = i_a + i_b + i_carry_in;
endmodule

Woche 9/alu_nzcv.sv
/**
 * ALU NZCV
 **/
module alu_nzcv #(parameter N=64) ( input  logic [N-1:0] i_a,
                                                         i_b,
                                    input  logic [1:0]   i_alu_ctrl,
                                    output logic [N-1:0] o_result,
                                    output logic [3:0]   o_nzcv );
  logic [N-1:0] l_b_tmp;
  logic [N-1:0] l_sum;
  logic [N-1:0] l_res_10;
  logic [N-1:0] l_res_11;
  logic         l_adder_carry;
  logic         l_compared_signs;
  logic         l_disable_ov;

  mux_2 #(N) mux_b( i_b,
                    ~i_b,
                    i_alu_ctrl[0],
                    l_b_tmp );
                    

  adder #(N) adder_ab( i_a,
                       l_b_tmp,
                       i_alu_ctrl[0],
                       l_sum,
                       l_adder_carry );

  assign l_res_10 = i_a & i_b;
  assign l_res_11 = i_a | i_b;

  mux_4 #(N) mux_result( l_sum,
                         l_sum,
                         l_res_10,
                         l_res_11,
                         i_alu_ctrl,
                         o_result );
                         
  assign o_nzcv[2] = &(~o_result);
  assign o_nzcv[3] = o_result[N-1];
  assign o_nzcv[1] = l_adder_carry & ~i_alu_ctrl[1];
  
  assign l_compared_signs = l_sum[N-1] ^ i_a[N-1];
  xor_3 ov_xor (i_a[N-1], i_b[N-1], i_alu_ctrl[0], l_disable_ov);
  
  assign o_nzcv[0] = ~i_alu_ctrl[1] & l_compared_signs & ~l_disable_ov;
  
endmodule

Woche 9/submission_22_06_12_boden_seppelt_orgler/alu_nzcv_tb.sv
module alu_nzcv_tb;

	logic [31:0] l_a, l_b, l_res;
	logic [1:0] l_alu_ctrl;
	logic [3:0] l_nzcv;	
	
	alu_nzcv #(32) dut ( l_a, l_b, l_alu_ctrl, l_res, l_nzcv);

	initial begin
	$dumpfile("dump_alu_nzcv.vcd");
	$dumpvars;
	
	l_a = 32'h0000_0000;
	l_b = 32'h0000_0000;
	l_alu_ctrl = 2'b00;
	#10;
	assert( l_res === 32'h0000_0000 );
	assert( l_nzcv === 4'b0100 );
	
	l_a = 32'h0000_0000;
	l_b = 32'hffff_ffff;
	l_alu_ctrl = 2'b00;
	#10;
	assert( l_res === 32'hffff_ffff );
	assert( l_nzcv === 4'b1000 );
	
	l_a = 32'h0000_0001;
	l_b = 32'hffff_ffff;
	l_alu_ctrl = 2'b00;
	#10;
	assert( l_res === 32'h0000_0000 );
	assert( l_nzcv === 4'b0110 );
	
	l_a = 32'h0000_ffff;
	l_b = 32'h0000_0001;
	l_alu_ctrl = 2'b00;
	#10;
	assert( l_res === 32'h0001_0000 );
	assert( l_nzcv === 4'b0000 );
	
	l_a = 32'h0000_0000;
	l_b = 32'h0000_0000;
	l_alu_ctrl = 2'b01;
	#10;
	assert( l_res === 32'h0000_0000 );
	assert( l_nzcv === 4'b0110 );
	
	l_a = 32'h0001_0000;
	l_b = 32'h0000_0001;
	l_alu_ctrl = 2'b01;
	#10;
	assert( l_res === 32'h0000_ffff );
	assert( l_nzcv === 4'b0010 );
	
	l_a = 32'hffff_ffff;
	l_b = 32'hffff_ffff;
	l_alu_ctrl = 2'b10;
	#10;
	assert( l_res === 32'hffff_ffff );
	assert( l_nzcv === 4'b1000 );
	
	l_a = 32'hffff_ffff;
	l_b = 32'h7743_3477;
	l_alu_ctrl = 2'b10;
	#10;
	assert( l_res === 32'h7743_3477 );
	assert( l_nzcv === 4'b0000 );
	
	l_a = 32'h0000_0000;
	l_b = 32'hffff_ffff;
	l_alu_ctrl = 2'b10;
	#10;
	assert( l_res === 32'h0000_0000 );
	assert( l_nzcv === 4'b0100 );
	
	l_a = 32'h0000_0000;
	l_b = 32'hffff_ffff;
	l_alu_ctrl = 2'b11;
	#10;
	assert( l_res === 32'hffff_ffff );
	assert( l_nzcv === 4'b1000 );
	

	
	$finish;
	end
endmodule

Woche 9/dump_alu_nzcv.vcd
$date
	Thu Jun  9 11:39:00 2022
$end
$version
	Icarus Verilog
$end
$timescale
	1s
$end
$scope module alu_nzcv_tb $end
$var wire 32 ! l_res [31:0] $end
$var wire 4 " l_nzcv [3:0] $end
$var reg 32 # l_a [31:0] $end
$var reg 2 $ l_alu_ctrl [1:0] $end
$var reg 32 % l_b [31:0] $end
$scope module dut $end
$var wire 32 & i_a [31:0] $end
$var wire 2 ' i_alu_ctrl [1:0] $end
$var wire 32 ( i_b [31:0] $end
$var wire 1 ) l_compared_signs $end
$var wire 32 * l_res_10 [31:0] $end
$var wire 32 + l_res_11 [31:0] $end
$var wire 32 , o_result [31:0] $end
$var wire 4 - o_nzcv [3:0] $end
$var wire 32 . l_sum [31:0] $end
$var wire 1 / l_disable_ov $end
$var wire 32 0 l_b_tmp [31:0] $end
$var wire 1 1 l_adder_carry $end
$scope module adder_ab $end
$var wire 32 2 i_a [31:0] $end
$var wire 1 3 i_carry_in $end
$var wire 1 1 o_carry_out $end
$var wire 32 4 o_c [31:0] $end
$var wire 32 5 i_b [31:0] $end
$upscope $end
$scope module mux_b $end
$var wire 32 6 i_in0 [31:0] $end
$var wire 32 7 i_in1 [31:0] $end
$var wire 1 8 i_s $end
$var wire 32 9 o_out [31:0] $end
$upscope $end
$scope module mux_result $end
$var wire 32 : i_in0 [31:0] $end
$var wire 32 ; i_in1 [31:0] $end
$var wire 32 < i_in2 [31:0] $end
$var wire 32 = i_in3 [31:0] $end
$var wire 2 > i_s [1:0] $end
$var wire 32 ? o_out [31:0] $end
$var wire 32 @ l_low [31:0] $end
$var wire 32 A l_high [31:0] $end
$scope module mux_final $end
$var wire 1 B i_s $end
$var wire 32 C o_out [31:0] $end
$var wire 32 D i_in1 [31:0] $end
$var wire 32 E i_in0 [31:0] $end
$upscope $end
$scope module mux_high $end
$var wire 32 F i_in0 [31:0] $end
$var wire 32 G i_in1 [31:0] $end
$var wire 1 H i_s $end
$var wire 32 I o_out [31:0] $end
$upscope $end
$scope module mux_low $end
$var wire 32 J i_in0 [31:0] $end
$var wire 32 K i_in1 [31:0] $end
$var wire 1 L i_s $end
$var wire 32 M o_out [31:0] $end
$upscope $end
$upscope $end
$scope module ov_xor $end
$var wire 1 N i_in0 $end
$var wire 1 O i_in1 $end
$var wire 1 P i_in2 $end
$var wire 1 Q l_res1 $end
$var wire 1 / o_res $end
$upscope $end
$upscope $end
$upscope $end
$scope module decoder $end
$var wire 4 R i_binary_number [3:0] $end
$var reg 7 S o_display [6:0] $end
$upscope $end
$enddefinitions $end
#0
$dumpvars
bx S
bz R
0Q
0P
0O
0N
b0 M
0L
b0 K
b0 J
b0 I
0H
b0 G
b0 F
b0 E
b0 D
b0 C
0B
b0 A
b0 @
b0 ?
b0 >
b0 =
b0 <
b0 ;
b0 :
b0 9
08
b11111111111111111111111111111111 7
b0 6
b0 5
b0 4
03
b0 2
01
b0 0
0/
b0 .
b100 -
b0 ,
b0 +
b0 *
0)
b0 (
b0 '
b0 &
b0 %
b0 $
b0 #
b100 "
b0 !
$end
#10
b1000 "
b1000 -
b11111111111111111111111111111111 !
b11111111111111111111111111111111 ,
b11111111111111111111111111111111 ?
b11111111111111111111111111111111 C
1)
1/
b11111111111111111111111111111111 @
b11111111111111111111111111111111 E
b11111111111111111111111111111111 M
1Q
b11111111111111111111111111111111 .
b11111111111111111111111111111111 4
b11111111111111111111111111111111 :
b11111111111111111111111111111111 ;
b11111111111111111111111111111111 J
b11111111111111111111111111111111 K
b0 7
b11111111111111111111111111111111 +
b11111111111111111111111111111111 =
b11111111111111111111111111111111 G
1O
b11111111111111111111111111111111 0
b11111111111111111111111111111111 5
b11111111111111111111111111111111 9
b11111111111111111111111111111111 %
b11111111111111111111111111111111 (
b11111111111111111111111111111111 6
#20
b0 !
b0 ,
b0 ?
b0 C
0)
b1 A
b1 D
b1 I
b0 @
b0 E
b0 M
b110 "
b110 -
b1 *
b1 <
b1 F
b0 .
b0 4
b0 :
b0 ;
b0 J
b0 K
11
b1 #
b1 &
b1 2
#30
0/
b0 "
b0 -
b10000000000000000 !
b10000000000000000 ,
b10000000000000000 ?
b10000000000000000 C
0Q
01
b10000000000000000 @
b10000000000000000 E
b10000000000000000 M
b11111111111111111111111111111110 7
0O
b1 0
b1 5
b1 9
b1111111111111111 +
b1111111111111111 =
b1111111111111111 G
b10000000000000000 .
b10000000000000000 4
b10000000000000000 :
b10000000000000000 ;
b10000000000000000 J
b10000000000000000 K
b1 %
b1 (
b1 6
b1111111111111111 #
b1111111111111111 &
b1111111111111111 2
#40
b110 "
b110 -
11
b0 !
b0 ,
b0 ?
b0 C
1/
b0 A
b0 D
b0 I
b0 @
b0 E
b0 M
18
13
1P
1L
1H
b11111111111111111111111111111111 7
b11111111111111111111111111111111 0
b11111111111111111111111111111111 5
b11111111111111111111111111111111 9
b0 *
b0 <
b0 F
b0 +
b0 =
b0 G
b0 .
b0 4
b0 :
b0 ;
b0 J
b0 K
b1 $
b1 '
b1 >
b0 %
b0 (
b0 6
b0 #
b0 &
b0 2
#50
b10 "
b10 -
b1111111111111111 !
b1111111111111111 ,
b1111111111111111 ?
b1111111111111111 C
b11111111111111111111111111111110 0
b11111111111111111111111111111110 5
b11111111111111111111111111111110 9
b10000000000000001 A
b10000000000000001 D
b10000000000000001 I
b1111111111111111 @
b1111111111111111 E
b1111111111111111 M
b11111111111111111111111111111110 7
b10000000000000001 +
b10000000000000001 =
b10000000000000001 G
b1111111111111111 .
b1111111111111111 4
b1111111111111111 :
b1111111111111111 ;
b1111111111111111 J
b1111111111111111 K
b1 %
b1 (
b1 6
b10000000000000000 #
b10000000000000000 &
b10000000000000000 2
#60
b1000 "
b1000 -
0/
b11111111111111111111111111111111 !
b11111111111111111111111111111111 ,
b11111111111111111111111111111111 ?
b11111111111111111111111111111111 C
b11111111111111111111111111111111 0
b11111111111111111111111111111111 5
b11111111111111111111111111111111 9
b11111111111111111111111111111111 A
b11111111111111111111111111111111 D
b11111111111111111111111111111111 I
b11111111111111111111111111111110 @
b11111111111111111111111111111110 E
b11111111111111111111111111111110 M
08
03
0P
0L
0H
1B
b0 7
1O
b11111111111111111111111111111111 *
b11111111111111111111111111111111 <
b11111111111111111111111111111111 F
b11111111111111111111111111111111 +
b11111111111111111111111111111111 =
b11111111111111111111111111111111 G
1N
b11111111111111111111111111111110 .
b11111111111111111111111111111110 4
b11111111111111111111111111111110 :
b11111111111111111111111111111110 ;
b11111111111111111111111111111110 J
b11111111111111111111111111111110 K
b10 $
b10 '
b10 >
b11111111111111111111111111111111 %
b11111111111111111111111111111111 (
b11111111111111111111111111111111 6
b11111111111111111111111111111111 #
b11111111111111111111111111111111 &
b11111111111111111111111111111111 2
#70
b0 "
b0 -
1)
b1110111010000110011010001110111 !
b1110111010000110011010001110111 ,
b1110111010000110011010001110111 ?
b1110111010000110011010001110111 C
1/
b1110111010000110011010001110110 @
b1110111010000110011010001110110 E
b1110111010000110011010001110110 M
b1110111010000110011010001110111 A
b1110111010000110011010001110111 D
b1110111010000110011010001110111 I
1Q
b1110111010000110011010001110110 .
b1110111010000110011010001110110 4
b1110111010000110011010001110110 :
b1110111010000110011010001110110 ;
b1110111010000110011010001110110 J
b1110111010000110011010001110110 K
b10001000101111001100101110001000 7
b1110111010000110011010001110111 *
b1110111010000110011010001110111 <
b1110111010000110011010001110111 F
0O
b1110111010000110011010001110111 0
b1110111010000110011010001110111 5
b1110111010000110011010001110111 9
b1110111010000110011010001110111 %
b1110111010000110011010001110111 (
b1110111010000110011010001110111 6
#80
b100 "
b100 -
b0 !
b0 ,
b0 ?
b0 C
b0 A
b0 D
b0 I
1)
b11111111111111111111111111111111 @
b11111111111111111111111111111111 E
b11111111111111111111111111111111 M
b0 7
1O
b11111111111111111111111111111111 0
b11111111111111111111111111111111 5
b11111111111111111111111111111111 9
b0 *
b0 <
b0 F
0N
b11111111111111111111111111111111 .
b11111111111111111111111111111111 4
b11111111111111111111111111111111 :
b11111111111111111111111111111111 ;
b11111111111111111111111111111111 J
b11111111111111111111111111111111 K
01
b11111111111111111111111111111111 %
b11111111111111111111111111111111 (
b11111111111111111111111111111111 6
b0 #
b0 &
b0 2
#90
0)
b1000 "
b1000 -
b1 @
b1 E
b1 M
b11111111111111111111111111111111 !
b11111111111111111111111111111111 ,
b11111111111111111111111111111111 ?
b11111111111111111111111111111111 C
b0 0
b0 5
b0 9
b1 .
b1 4
b1 :
b1 ;
b1 J
b1 K
01
0/
b11111111111111111111111111111111 A
b11111111111111111111111111111111 D
b11111111111111111111111111111111 I
18
13
1P
1L
1H
b11 $
b11 '
b11 >
